samsungwsctl.py
samsungwsctl-1.0.7.dist-info/LICENSE
samsungwsctl-1.0.7.dist-info/METADATA
samsungwsctl-1.0.7.dist-info/WHEEL
samsungwsctl-1.0.7.dist-info/top_level.txt
samsungwsctl-1.0.7.dist-info/RECORD
