Metadata-Version: 2.1
Name: samsungwsctl
Version: 1.0.7
Summary: A minimal alternative to samsungctl for controlling newer Samsung Smart TVs.
Home-page: https://github.com/nickw444/samsungwsctl
Author: Nick Whyte
Author-email: nick@nickwhyte.com
License: UNKNOWN
Platform: UNKNOWN
Classifier: Intended Audience :: Developers
Classifier: Programming Language :: Python
License-File: LICENSE
Requires-Dist: websocket-client (~=0.57.0)
Requires-Dist: requests (<3.0.0,>=2.22.0)
